hpb_mumc_dashboard/__init__.py
hpb_mumc_dashboard/hpb_mumc_dashboard.py
hpb_mumc_dashboard/dashboard/__init__.py
hpb_mumc_dashboard/etl/__init__.py
hpb_mumc_dashboard/etl/script_runner.py
hpb_mumc_dashboard/etl/scripts/BaseScript.py
hpb_mumc_dashboard/etl/scripts/DummyScript.py
hpb_mumc_dashboard/etl/scripts/RetrieveProcedureCountsAndComplicationsPerQuarterScript.py
hpb_mumc_dashboard/etl/scripts/RetrieveStudyListScript.py
hpb_mumc_dashboard/etl/scripts/__init__.py
hpb_mumc_dashboard-0.2.0.dist-info/METADATA
hpb_mumc_dashboard-0.2.0.dist-info/WHEEL
hpb_mumc_dashboard-0.2.0.dist-info/entry_points.txt
hpb_mumc_dashboard-0.2.0.dist-info/top_level.txt
hpb_mumc_dashboard-0.2.0.dist-info/RECORD
