Metadata-Version: 2.1
Name: hpb-mumc-dashboard
Version: 0.2.0
Summary: Python Boilerplate contains all the boilerplate you need to create a Python package.
Home-page: https://github.com/rbrecheisen/hpb_mumc_dashboard
Author: Ralph Brecheisen
Author-email: r.brecheisen@maastrichtuniversity.nl
License: UNKNOWN
Keywords: hpb_mumc_dashboard
Platform: UNKNOWN
Classifier: Development Status :: 2 - Pre-Alpha
Classifier: Intended Audience :: Developers
Classifier: Natural Language :: English
Classifier: Programming Language :: Python :: 3
Classifier: Programming Language :: Python :: 3.5
Classifier: Programming Language :: Python :: 3.6
Classifier: Programming Language :: Python :: 3.7
Classifier: Programming Language :: Python :: 3.8
Requires-Python: >=3.5
Requires-Dist: pytest
Requires-Dist: barbell2
Requires-Dist: bokeh
Requires-Dist: django
